fitness_tracker/__init__.py
fitness_tracker/__main__.py
fitness_tracker/database_wrapper.py
fitness_tracker/fitness_tracker.db
fitness_tracker/icon.png
fitness_tracker/iconorig.png
fitness_tracker/settings.py
fitness_tracker/titlebar.py
fitness_tracker/calculators/__init__.py
fitness_tracker/calculators/body_fat/__init__.py
fitness_tracker/calculators/body_fat/body_fat.py
fitness_tracker/calculators/body_fat/body_fat_calculator.py
fitness_tracker/calculators/body_fat/body_fat_formulas.py
fitness_tracker/calculators/body_fat/main_panel.py
fitness_tracker/calculators/one_rep_max/__init__.py
fitness_tracker/calculators/one_rep_max/main_panel.py
fitness_tracker/calculators/one_rep_max/one_rep_max.py
fitness_tracker/calculators/one_rep_max/one_rep_max_calculator.py
fitness_tracker/calculators/strength_estimator/__init__.py
fitness_tracker/calculators/strength_estimator/estimator.py
fitness_tracker/calculators/strength_estimator/exercise_standards.py
fitness_tracker/calculators/strength_estimator/main_panel.py
fitness_tracker/calculators/strength_estimator/strength_estimator.py
fitness_tracker/common/__init__.py
fitness_tracker/common/units_conversion.py
fitness_tracker/font/Montserrat-Regular.ttf
fitness_tracker/font/Ubuntu-Regular.ttf
fitness_tracker/homepage/__init__.py
fitness_tracker/homepage/header.py
fitness_tracker/homepage/side_panel.py
fitness_tracker/homepage/icons/big_lifts.png
fitness_tracker/homepage/icons/body_fat.png
fitness_tracker/homepage/icons/calories.png
fitness_tracker/homepage/icons/home.png
fitness_tracker/homepage/icons/logout.png
fitness_tracker/homepage/icons/one_rep_max.png
fitness_tracker/homepage/icons/strength.png
fitness_tracker/homepage/icons/strength_es.png
fitness_tracker/homepage/icons/user.png
fitness_tracker/homepage/icons/weight_loss.png
fitness_tracker/homepage/icons/workouts.png
fitness_tracker/icons/close.bmp
fitness_tracker/icons/darrow.png
fitness_tracker/icons/ftarizonacalligraphy.png
fitness_tracker/icons/max.bmp
fitness_tracker-1.0.1.dist-info/LICENSE
fitness_tracker-1.0.1.dist-info/METADATA
fitness_tracker-1.0.1.dist-info/WHEEL
fitness_tracker-1.0.1.dist-info/top_level.txt
fitness_tracker-1.0.1.dist-info/RECORD
