Metadata-Version: 2.1
Name: fitness-tracker
Version: 1.0.1
Summary: Fitness Tracker is a tool that offers a better way of tracking your fitness progress.
Home-page: https://github.com/JuricaRT/fitness_tracker
Author: Jurica Runtas, Kristijan Milić
License: MIT
Platform: UNKNOWN
Classifier: Programming Language :: Python :: 3
Classifier: License :: OSI Approved :: MIT License
Classifier: Operating System :: OS Independent
Requires-Python: >=3.6
Requires-Dist: PyQt5
Requires-Dist: requests
Requires-Dist: psycopg2
Requires-Dist: matplotlib
Requires-Dist: numpy
